{
 "activities": [
  {
   "id": "19408137429",
   "name": "Course à pied en soirée",
   "description": "",
   "sport_type": "Run",
   "start_local": "2026-07-21T20:15:42",
   "summary": {
    "distance": 11008.1,
    "moving_time": 3372,
    "elapsed_time": 3415,
    "elevation_gain": 54.0,
    "avg_speed": 3.265,
    "max_speed": 5.52,
    "avg_cadence": 88.8,
    "relative_effort": 82.0,
    "total_calories": 801.0,
    "kudos_count": 0,
    "achievement_count": 0,
    "pr_count": 0
   },
   "performance": {
    "average_heartrate": 148.7,
    "max_heartrate": 164.0,
    "average_watts": 368.5,
    "laps": [
     {
      "elapsed_time": 332,
      "moving_time": 332,
      "distance": 1000.0,
      "avg_hr": 127.3,
      "avg_cadence": 178,
      "avg_watts": 344.0
     },
     {
      "elapsed_time": 306,
      "moving_time": 306,
      "distance": 1000.0,
      "avg_hr": 142.9,
      "avg_cadence": 178,
      "avg_watts": 365.9
     },
     {
      "elapsed_time": 308,
      "moving_time": 308,
      "distance": 1000.0,
      "avg_hr": 146.1,
      "avg_cadence": 178,
      "avg_watts": 361.8
     },
     {
      "elapsed_time": 304,
      "moving_time": 304,
      "distance": 1000.0,
      "avg_hr": 148.3,
      "avg_cadence": 178,
      "avg_watts": 365.0
     },
     {
      "elapsed_time": 298,
      "moving_time": 298,
      "distance": 1000.0,
      "avg_hr": 153.4,
      "avg_cadence": 178,
      "avg_watts": 363.8
     },
     {
      "elapsed_time": 343,
      "moving_time": 299,
      "distance": 1000.0,
      "avg_hr": 154.1,
      "avg_cadence": 177,
      "avg_watts": 388.8
     },
     {
      "elapsed_time": 300,
      "moving_time": 300,
      "distance": 1000.0,
      "avg_hr": 150.4,
      "avg_cadence": 179,
      "avg_watts": 376.2
     },
     {
      "elapsed_time": 301,
      "moving_time": 301,
      "distance": 1000.0,
      "avg_hr": 150.9,
      "avg_cadence": 178,
      "avg_watts": 352.0
     },
     {
      "elapsed_time": 303,
      "moving_time": 303,
      "distance": 1000.0,
      "avg_hr": 152.4,
      "avg_cadence": 177,
      "avg_watts": 362.7
     },
     {
      "elapsed_time": 306,
      "moving_time": 306,
      "distance": 1000.0,
      "avg_hr": 156.4,
      "avg_cadence": 176,
      "avg_watts": 386.4
     },
     {
      "elapsed_time": 307,
      "moving_time": 307,
      "distance": 1000.0,
      "avg_hr": 155.3,
      "avg_cadence": 177,
      "avg_watts": 389.6
     },
     {
      "elapsed_time": 2,
      "moving_time": 2,
      "distance": 8.07,
      "avg_hr": 157.0,
      "avg_cadence": 172,
      "avg_watts": 393.0
     }
    ]
   }
  }
 ]
}